{
  "$schema": "https://developer.microsoft.com/json-schemas/fabric/item/report/definition/visualContainer/2.11.0/schema.json",
  "name": "0a90094a86cdaf091fba",
  "position": {
    "x": 27.5,
    "y": 202.5,
    "z": 23000,
    "height": 142.5,
    "width": 210,
    "tabOrder": 23000
  },
  "visual": {
    "visualType": "pageNavigator",
    "objects": {
      "layout": [
        {
          "properties": {
            "orientation": {
              "expr": {
                "Literal": {
                  "Value": "1D"
                }
              }
            },
            "cellPadding": {
              "expr": {
                "Literal": {
                  "Value": "10L"
                }
              }
            }
          }
        }
      ],
      "text": [
        {
          "properties": {
            "fontFamily": {
              "expr": {
                "Literal": {
                  "Value": "'''Segoe UI Bold'', wf_segoe-ui_bold, helvetica, arial, sans-serif'"
                }
              }
            },
            "fontSize": {
              "expr": {
                "Literal": {
                  "Value": "11D"
                }
              }
            }
          },
          "selector": {
            "id": "default"
          }
        }
      ],
      "fill": [
        {
          "properties": {
            "fillColor": {
              "solid": {
                "color": {
                  "expr": {
                    "ThemeDataColor": {
                      "ColorId": 8,
                      "Percent": 0.6
                    }
                  }
                }
              }
            }
          },
          "selector": {
            "id": "press"
          }
        },
        {
          "properties": {
            "fillColor": {
              "solid": {
                "color": {
                  "expr": {
                    "ThemeDataColor": {
                      "ColorId": 2,
                      "Percent": 0.2
                    }
                  }
                }
              }
            }
          },
          "selector": {
            "id": "selected"
          }
        }
      ]
    },
    "drillFilterOtherVisuals": true
  },
  "howCreated": "InsertVisualButton"
}